{
  "665489": {
    "position": "1B",
    "fetched": "2026-05-06"
  },
  "514888": {
    "position": "2B",
    "fetched": "2026-05-06"
  },
  "665862": {
    "position": "2B",
    "fetched": "2026-05-06"
  },
  "621043": {
    "position": "SS",
    "fetched": "2026-05-06"
  },
  "695657": {
    "position": "SS",
    "fetched": "2026-05-06"
  },
  "572233": {
    "position": "1B",
    "fetched": "2026-05-06"
  },
  "676724": {
    "position": "1B",
    "fetched": "2026-05-06"
  },
  "805367": {
    "position": "2B",
    "fetched": "2026-05-06"
  },
  "670541": {
    "position": "DH",
    "fetched": "2026-05-06"
  },
  "680718": {
    "position": "RF",
    "fetched": "2026-05-06"
  },
  "543807": {
    "position": "DH",
    "fetched": "2026-05-06"
  },
  "673237": {
    "position": "C",
    "fetched": "2026-05-06"
  },
  "808959": {
    "position": "1B",
    "fetched": "2026-05-06"
  },
  "700337": {
    "position": "C",
    "fetched": "2026-05-06"
  },
  "701358": {
    "position": "RF",
    "fetched": "2026-05-06"
  },
  "673357": {
    "position": "CF",
    "fetched": "2026-05-06"
  },
  "677592": {
    "position": "RF",
    "fetched": "2026-05-06"
  },
  "678246": {
    "position": "3B",
    "fetched": "2026-05-06"
  },
  "676694": {
    "position": "CF",
    "fetched": "2026-05-06"
  },
  "672960": {
    "position": "3B",
    "fetched": "2026-05-06"
  },
  "671739": {
    "position": "CF",
    "fetched": "2026-05-06"
  },
  "682668": {
    "position": "CF",
    "fetched": "2026-05-06"
  },
  "686948": {
    "position": "C",
    "fetched": "2026-05-06"
  },
  "683146": {
    "position": "RF",
    "fetched": "2026-05-06"
  },
  "543877": {
    "position": "C",
    "fetched": "2026-05-06"
  },
  "641680": {
    "position": "C",
    "fetched": "2026-05-06"
  },
  "663586": {
    "position": "3B",
    "fetched": "2026-05-06"
  },
  "621566": {
    "position": "1B",
    "fetched": "2026-05-06"
  },
  "596019": {
    "position": "SS",
    "fetched": "2026-05-06"
  },
  "643217": {
    "position": "DH",
    "fetched": "2026-05-06"
  },
  "803011": {
    "position": "LF",
    "fetched": "2026-05-06"
  },
  "665161": {
    "position": "SS",
    "fetched": "2026-05-06"
  },
  "543760": {
    "position": "2B",
    "fetched": "2026-05-06"
  },
  "662139": {
    "position": "CF",
    "fetched": "2026-05-06"
  },
  "694388": {
    "position": "LF",
    "fetched": "2026-05-06"
  },
  "519317": {
    "position": "DH",
    "fetched": "2026-05-06"
  },
  "660670": {
    "position": "RF",
    "fetched": "2026-05-06"
  },
  "669394": {
    "position": "1B",
    "fetched": "2026-05-06"
  },
  "672386": {
    "position": "C",
    "fetched": "2026-05-06"
  },
  "543309": {
    "position": "C",
    "fetched": "2026-05-06"
  },
  "645277": {
    "position": "2B",
    "fetched": "2026-05-06"
  },
  "669701": {
    "position": "2B",
    "fetched": "2026-05-06"
  },
  "573262": {
    "position": "LF",
    "fetched": "2026-05-06"
  },
  "669397": {
    "position": "SS",
    "fetched": "2026-05-06"
  },
  "592626": {
    "position": "DH",
    "fetched": "2026-05-06"
  },
  "673962": {
    "position": "3B",
    "fetched": "2026-05-06"
  },
  "663728": {
    "position": "C",
    "fetched": "2026-05-06"
  },
  "701807": {
    "position": "RF",
    "fetched": "2026-05-06"
  },
  "702284": {
    "position": "2B",
    "fetched": "2026-05-06"
  },
  "665926": {
    "position": "SS",
    "fetched": "2026-05-06"
  },
  "694497": {
    "position": "CF",
    "fetched": "2026-05-06"
  },
  "621438": {
    "position": "RF",
    "fetched": "2026-05-06"
  },
  "643376": {
    "position": "C",
    "fetched": "2026-05-06"
  },
  "641598": {
    "position": "C",
    "fetched": "2026-05-06"
  },
  "672580": {
    "position": "3B",
    "fetched": "2026-05-06"
  },
  "641857": {
    "position": "3B",
    "fetched": "2026-05-06"
  },
  "660844": {
    "position": "3B",
    "fetched": "2026-05-06"
  },
  "664059": {
    "position": "LF",
    "fetched": "2026-05-06"
  },
  "620443": {
    "position": "C",
    "fetched": "2026-05-06"
  },
  "664728": {
    "position": "CF",
    "fetched": "2026-05-06"
  },
  "676391": {
    "position": "2B",
    "fetched": "2026-05-06"
  },
  "641555": {
    "position": "C",
    "fetched": "2026-05-06"
  },
  "679845": {
    "position": "2B",
    "fetched": "2026-05-06"
  },
  "677594": {
    "position": "CF",
    "fetched": "2026-05-06"
  },
  "677649": {
    "position": "2B",
    "fetched": "2026-05-06"
  },
  "670042": {
    "position": "RF",
    "fetched": "2026-05-06"
  },
  "666182": {
    "position": "3B",
    "fetched": "2026-05-06"
  },
  "642708": {
    "position": "3B",
    "fetched": "2026-05-06"
  },
  "607043": {
    "position": "RF",
    "fetched": "2026-05-06"
  },
  "677951": {
    "position": "SS",
    "fetched": "2026-05-06"
  },
  "656537": {
    "position": "RF",
    "fetched": "2026-05-06"
  },
  "608701": {
    "position": "RF",
    "fetched": "2026-05-06"
  },
  "668227": {
    "position": "LF",
    "fetched": "2026-05-06"
  },
  "686527": {
    "position": "DH",
    "fetched": "2026-05-06"
  },
  "686469": {
    "position": "1B",
    "fetched": "2026-05-06"
  },
  "641487": {
    "position": "SS",
    "fetched": "2026-05-06"
  },
  "592450": {
    "position": "RF",
    "fetched": "2026-05-06"
  },
  "669224": {
    "position": "C",
    "fetched": "2026-05-06"
  },
  "657041": {
    "position": "CF",
    "fetched": "2026-05-06"
  },
  "643289": {
    "position": "SS",
    "fetched": "2026-05-06"
  },
  "663757": {
    "position": "CF",
    "fetched": "2026-05-06"
  },
  "695506": {
    "position": "RF",
    "fetched": "2026-05-06"
  },
  "641355": {
    "position": "LF",
    "fetched": "2026-05-06"
  },
  "700250": {
    "position": "1B",
    "fetched": "2026-05-06"
  },
  "521692": {
    "position": "C",
    "fetched": "2026-05-06"
  },
  "676609": {
    "position": "SS",
    "fetched": "2026-05-06"
  },
  "642086": {
    "position": "DH",
    "fetched": "2026-05-06"
  },
  "593871": {
    "position": "DH",
    "fetched": "2026-05-06"
  },
  "686555": {
    "position": "LF",
    "fetched": "2026-05-06"
  },
  "647304": {
    "position": "1B",
    "fetched": "2026-05-06"
  },
  "694376": {
    "position": "3B",
    "fetched": "2026-05-06"
  },
  "682626": {
    "position": "C",
    "fetched": "2026-05-06"
  },
  "694728": {
    "position": "LF",
    "fetched": "2026-05-06"
  },
  "608369": {
    "position": "SS",
    "fetched": "2026-05-06"
  },
  "660821": {
    "position": "RF",
    "fetched": "2026-05-06"
  },
  "677595": {
    "position": "SS",
    "fetched": "2026-05-06"
  },
  "623168": {
    "position": "C",
    "fetched": "2026-05-06"
  },
  "694671": {
    "position": "LF",
    "fetched": "2026-05-06"
  },
  "696030": {
    "position": "LF",
    "fetched": "2026-05-06"
  },
  "664770": {
    "position": "RF",
    "fetched": "2026-05-06"
  },
  "457705": {
    "position": "DH",
    "fetched": "2026-05-06"
  },
  "624512": {
    "position": "C",
    "fetched": "2026-05-06"
  },
  "668901": {
    "position": "1B",
    "fetched": "2026-05-06"
  },
  "686681": {
    "position": "2B",
    "fetched": "2026-05-06"
  },
  "642201": {
    "position": "LF",
    "fetched": "2026-05-06"
  },
  "695600": {
    "position": "C",
    "fetched": "2026-05-06"
  },
  "671976": {
    "position": "CF",
    "fetched": "2026-05-06"
  },
  "664702": {
    "position": "RF",
    "fetched": "2026-05-06"
  },
  "676914": {
    "position": "LF",
    "fetched": "2026-05-06"
  },
  "545341": {
    "position": "LF",
    "fetched": "2026-05-06"
  },
  "695020": {
    "position": "LF",
    "fetched": "2026-05-06"
  },
  "643396": {
    "position": "2B",
    "fetched": "2026-05-06"
  },
  "678882": {
    "position": "CF",
    "fetched": "2026-05-06"
  },
  "575929": {
    "position": "1B",
    "fetched": "2026-05-06"
  },
  "702332": {
    "position": "3B",
    "fetched": "2026-05-06"
  },
  "596115": {
    "position": "SS",
    "fetched": "2026-05-06"
  },
  "657136": {
    "position": "C",
    "fetched": "2026-05-06"
  },
  "680776": {
    "position": "LF",
    "fetched": "2026-05-06"
  },
  "655316": {
    "position": "1B",
    "fetched": "2026-05-06"
  },
  "677800": {
    "position": "RF",
    "fetched": "2026-05-06"
  },
  "800050": {
    "position": "RF",
    "fetched": "2026-05-06"
  },
  "656305": {
    "position": "3B",
    "fetched": "2026-05-06"
  },
  "700932": {
    "position": "1B",
    "fetched": "2026-05-06"
  },
  "694377": {
    "position": "3B",
    "fetched": "2026-05-06"
  },
  "808982": {
    "position": "RF",
    "fetched": "2026-05-06"
  },
  "664056": {
    "position": "CF",
    "fetched": "2026-05-06"
  },
  "656811": {
    "position": "RF",
    "fetched": "2026-05-06"
  },
  "650333": {
    "position": "2B",
    "fetched": "2026-05-06"
  },
  "682657": {
    "position": "LF",
    "fetched": "2026-05-06"
  },
  "646240": {
    "position": "1B",
    "fetched": "2026-05-06"
  },
  "656555": {
    "position": "1B",
    "fetched": "2026-05-06"
  },
  "666310": {
    "position": "C",
    "fetched": "2026-05-06"
  },
  "668804": {
    "position": "LF",
    "fetched": "2026-05-06"
  },
  "642715": {
    "position": "SS",
    "fetched": "2026-05-06"
  },
  "608070": {
    "position": "3B",
    "fetched": "2026-05-06"
  },
  "669477": {
    "position": "DH",
    "fetched": "2026-05-06"
  },
  "680779": {
    "position": "C",
    "fetched": "2026-05-06"
  },
  "804606": {
    "position": "SS",
    "fetched": "2026-05-06"
  },
  "664040": {
    "position": "2B",
    "fetched": "2026-05-06"
  },
  "671218": {
    "position": "LF",
    "fetched": "2026-05-06"
  },
  "680757": {
    "position": "CF",
    "fetched": "2026-05-06"
  },
  "665833": {
    "position": "CF",
    "fetched": "2026-05-06"
  },
  "682177": {
    "position": "CF",
    "fetched": "2026-05-06"
  },
  "682877": {
    "position": "2B",
    "fetched": "2026-05-06"
  },
  "663968": {
    "position": "LF",
    "fetched": "2026-05-06"
  },
  "687462": {
    "position": "1B",
    "fetched": "2026-05-06"
  },
  "672275": {
    "position": "C",
    "fetched": "2026-05-06"
  },
  "668904": {
    "position": "3B",
    "fetched": "2026-05-06"
  },
  "807712": {
    "position": "2B",
    "fetched": "2026-05-06"
  },
  "621439": {
    "position": "CF",
    "fetched": "2026-05-06"
  },
  "693304": {
    "position": "3B",
    "fetched": "2026-05-06"
  },
  "687957": {
    "position": "LF",
    "fetched": "2026-05-06"
  },
  "542303": {
    "position": "DH",
    "fetched": "2026-05-06"
  },
  "656484": {
    "position": "3B",
    "fetched": "2026-05-06"
  },
  "670623": {
    "position": "3B",
    "fetched": "2026-05-06"
  },
  "663616": {
    "position": "LF",
    "fetched": "2026-05-06"
  },
  "670242": {
    "position": "RF",
    "fetched": "2026-05-06"
  },
  "665019": {
    "position": "1B",
    "fetched": "2026-05-06"
  },
  "677587": {
    "position": "SS",
    "fetched": "2026-05-06"
  },
  "605170": {
    "position": "C",
    "fetched": "2026-05-06"
  },
  "605137": {
    "position": "DH",
    "fetched": "2026-05-06"
  },
  "595978": {
    "position": "C",
    "fetched": "2026-05-06"
  },
  "663698": {
    "position": "C",
    "fetched": "2026-05-06"
  },
  "671655": {
    "position": "LF",
    "fetched": "2026-05-06"
  },
  "680728": {
    "position": "C",
    "fetched": "2026-05-06"
  },
  "672695": {
    "position": "SS",
    "fetched": "2026-05-06"
  },
  "606466": {
    "position": "2B",
    "fetched": "2026-05-06"
  },
  "678489": {
    "position": "LF",
    "fetched": "2026-05-06"
  },
  "701350": {
    "position": "LF",
    "fetched": "2026-05-06"
  },
  "545121": {
    "position": "1B",
    "fetched": "2026-05-06"
  },
  "699912": {
    "position": "DH",
    "fetched": "2026-05-06"
  },
  "682998": {
    "position": "RF",
    "fetched": "2026-05-06"
  },
  "680777": {
    "position": "C",
    "fetched": "2026-05-06"
  },
  "677950": {
    "position": "CF",
    "fetched": "2026-05-06"
  },
  "669707": {
    "position": "SS",
    "fetched": "2026-05-06"
  },
  "691785": {
    "position": "2B",
    "fetched": "2026-05-06"
  },
  "686797": {
    "position": "SS",
    "fetched": "2026-05-06"
  },
  "571448": {
    "position": "3B",
    "fetched": "2026-05-06"
  },
  "663609": {
    "position": "1B",
    "fetched": "2026-05-06"
  },
  "807799": {
    "position": "DH",
    "fetched": "2026-05-06"
  },
  "665966": {
    "position": "C",
    "fetched": "2026-05-06"
  },
  "681807": {
    "position": "RF",
    "fetched": "2026-05-06"
  },
  "553869": {
    "position": "C",
    "fetched": "2026-05-06"
  },
  "543510": {
    "position": "C",
    "fetched": "2026-05-06"
  },
  "694374": {
    "position": "LF",
    "fetched": "2026-05-06"
  },
  "681546": {
    "position": "LF",
    "fetched": "2026-05-06"
  },
  "691740": {
    "position": "C",
    "fetched": "2026-05-06"
  },
  "672820": {
    "position": "DH",
    "fetched": "2026-05-06"
  },
  "683766": {
    "position": "2B",
    "fetched": "2026-05-06"
  },
  "666464": {
    "position": "RF",
    "fetched": "2026-05-06"
  },
  "668885": {
    "position": "LF",
    "fetched": "2026-05-06"
  },
  "666931": {
    "position": "CF",
    "fetched": "2026-05-06"
  },
  "669720": {
    "position": "LF",
    "fetched": "2026-05-06"
  },
  "663837": {
    "position": "CF",
    "fetched": "2026-05-06"
  },
  "682985": {
    "position": "LF",
    "fetched": "2026-05-06"
  },
  "681481": {
    "position": "RF",
    "fetched": "2026-05-06"
  },
  "701678": {
    "position": "3B",
    "fetched": "2026-05-06"
  },
  "595879": {
    "position": "SS",
    "fetched": "2026-05-06"
  },
  "679529": {
    "position": "1B",
    "fetched": "2026-05-06"
  },
  "693307": {
    "position": "C",
    "fetched": "2026-05-06"
  },
  "672761": {
    "position": "RF",
    "fetched": "2026-05-06"
  },
  "650402": {
    "position": "2B",
    "fetched": "2026-05-06"
  },
  "624413": {
    "position": "1B",
    "fetched": "2026-05-06"
  },
  "665750": {
    "position": "CF",
    "fetched": "2026-05-06"
  },
  "691723": {
    "position": "3B",
    "fetched": "2026-05-06"
  },
  "802139": {
    "position": "2B",
    "fetched": "2026-05-06"
  },
  "691023": {
    "position": "RF",
    "fetched": "2026-05-06"
  },
  "621493": {
    "position": "LF",
    "fetched": "2026-05-06"
  },
  "668939": {
    "position": "C",
    "fetched": "2026-05-06"
  },
  "683002": {
    "position": "SS",
    "fetched": "2026-05-06"
  },
  "602104": {
    "position": "3B",
    "fetched": "2026-05-06"
  },
  "676475": {
    "position": "1B",
    "fetched": "2026-05-06"
  },
  "805808": {
    "position": "SS",
    "fetched": "2026-05-06"
  },
  "669236": {
    "position": "2B",
    "fetched": "2026-05-06"
  },
  "694212": {
    "position": "C",
    "fetched": "2026-05-06"
  },
  "592885": {
    "position": "DH",
    "fetched": "2026-05-06"
  },
  "669357": {
    "position": "3B",
    "fetched": "2026-05-06"
  },
  "671056": {
    "position": "DH",
    "fetched": "2026-05-06"
  },
  "687363": {
    "position": "CF",
    "fetched": "2026-05-06"
  },
  "668930": {
    "position": "2B",
    "fetched": "2026-05-06"
  },
  "695336": {
    "position": "LF",
    "fetched": "2026-05-06"
  },
  "669003": {
    "position": "CF",
    "fetched": "2026-05-06"
  },
  "665877": {
    "position": "LF",
    "fetched": "2026-05-06"
  },
  "687637": {
    "position": "RF",
    "fetched": "2026-05-06"
  },
  "661388": {
    "position": "C",
    "fetched": "2026-05-06"
  },
  "686217": {
    "position": "RF",
    "fetched": "2026-05-06"
  },
  "650859": {
    "position": "3B",
    "fetched": "2026-05-06"
  },
  "690993": {
    "position": "3B",
    "fetched": "2026-05-06"
  },
  "668670": {
    "position": "C",
    "fetched": "2026-05-06"
  },
  "663368": {
    "position": "CF",
    "fetched": "2026-05-06"
  },
  "666152": {
    "position": "3B",
    "fetched": "2026-05-06"
  },
  "641343": {
    "position": "1B",
    "fetched": "2026-05-06"
  },
  "682622": {
    "position": "RF",
    "fetched": "2026-05-06"
  },
  "663330": {
    "position": "DH",
    "fetched": "2026-05-06"
  },
  "663886": {
    "position": "C",
    "fetched": "2026-05-06"
  },
  "657656": {
    "position": "LF",
    "fetched": "2026-05-06"
  },
  "592518": {
    "position": "3B",
    "fetched": "2026-05-06"
  },
  "665487": {
    "position": "RF",
    "fetched": "2026-05-06"
  },
  "668715": {
    "position": "LF",
    "fetched": "2026-05-06"
  },
  "701538": {
    "position": "CF",
    "fetched": "2026-05-06"
  },
  "592206": {
    "position": "DH",
    "fetched": "2026-05-06"
  },
  "667472": {
    "position": "CF",
    "fetched": "2026-05-06"
  },
  "553993": {
    "position": "DH",
    "fetched": "2026-05-06"
  },
  "641933": {
    "position": "RF",
    "fetched": "2026-05-06"
  },
  "630105": {
    "position": "2B",
    "fetched": "2026-05-06"
  },
  "593428": {
    "position": "SS",
    "fetched": "2026-05-06"
  },
  "682641": {
    "position": "RF",
    "fetched": "2026-05-06"
  },
  "609280": {
    "position": "DH",
    "fetched": "2026-05-06"
  },
  "680574": {
    "position": "2B",
    "fetched": "2026-05-06"
  },
  "670770": {
    "position": "CF",
    "fetched": "2026-05-06"
  },
  "663647": {
    "position": "3B",
    "fetched": "2026-05-06"
  },
  "682829": {
    "position": "SS",
    "fetched": "2026-05-06"
  },
  "650968": {
    "position": "C",
    "fetched": "2026-05-06"
  },
  "669369": {
    "position": "LF",
    "fetched": "2026-05-06"
  },
  "663604": {
    "position": "LF",
    "fetched": "2026-05-06"
  },
  "677942": {
    "position": "3B",
    "fetched": "2026-05-06"
  },
  "596142": {
    "position": "DH",
    "fetched": "2026-05-06"
  },
  "687401": {
    "position": "SS",
    "fetched": "2026-05-06"
  },
  "668952": {
    "position": "3B",
    "fetched": "2026-05-06"
  },
  "701398": {
    "position": "1B",
    "fetched": "2026-05-06"
  },
  "686780": {
    "position": "C",
    "fetched": "2026-05-06"
  },
  "691026": {
    "position": "SS",
    "fetched": "2026-05-06"
  },
  "666023": {
    "position": "C",
    "fetched": "2026-05-06"
  },
  "664034": {
    "position": "1B",
    "fetched": "2026-05-06"
  },
  "669134": {
    "position": "C",
    "fetched": "2026-05-06"
  },
  "624431": {
    "position": "C",
    "fetched": "2026-05-06"
  },
  "666181": {
    "position": "RF",
    "fetched": "2026-05-06"
  },
  "657757": {
    "position": "1B",
    "fetched": "2026-05-06"
  },
  "650391": {
    "position": "DH",
    "fetched": "2026-05-06"
  },
  "502671": {
    "position": "1B",
    "fetched": "2026-05-06"
  },
  "701675": {
    "position": "LF",
    "fetched": "2026-05-06"
  },
  "682818": {
    "position": "LF",
    "fetched": "2026-05-06"
  },
  "681297": {
    "position": "RF",
    "fetched": "2026-05-06"
  },
  "663993": {
    "position": "DH",
    "fetched": "2026-05-06"
  },
  "660271": {
    "position": "DH",
    "fetched": "2026-05-06"
  },
  "663697": {
    "position": "2B",
    "fetched": "2026-05-06"
  },
  "571657": {
    "position": "DH",
    "fetched": "2026-05-06"
  },
  "663656": {
    "position": "RF",
    "fetched": "2026-05-06"
  },
  "571970": {
    "position": "3B",
    "fetched": "2026-05-06"
  },
  "681624": {
    "position": "CF",
    "fetched": "2026-05-06"
  },
  "669257": {
    "position": "C",
    "fetched": "2026-05-06"
  },
  "605141": {
    "position": "SS",
    "fetched": "2026-05-06"
  },
  "606192": {
    "position": "LF",
    "fetched": "2026-05-06"
  },
  "622761": {
    "position": "SS",
    "fetched": "2026-05-06"
  },
  "500743": {
    "position": "SS",
    "fetched": "2026-05-06"
  },
  "663897": {
    "position": "2B",
    "fetched": "2026-05-06"
  },
  "518692": {
    "position": "1B",
    "fetched": "2026-05-06"
  },
  "663538": {
    "position": "2B",
    "fetched": "2026-05-06"
  },
  "690976": {
    "position": "2B",
    "fetched": "2026-05-06"
  },
  "680977": {
    "position": "3B",
    "fetched": "2026-05-06"
  },
  "608324": {
    "position": "3B",
    "fetched": "2026-05-06"
  },
  "694208": {
    "position": "DH",
    "fetched": "2026-05-06"
  },
  "807713": {
    "position": "RF",
    "fetched": "2026-05-06"
  },
  "608348": {
    "position": "C",
    "fetched": "2026-05-06"
  },
  "621020": {
    "position": "SS",
    "fetched": "2026-05-06"
  },
  "683737": {
    "position": "1B",
    "fetched": "2026-05-06"
  },
  "664023": {
    "position": "LF",
    "fetched": "2026-05-06"
  },
  "810938": {
    "position": "2B",
    "fetched": "2026-05-06"
  },
  "663743": {
    "position": "C",
    "fetched": "2026-05-06"
  },
  "656775": {
    "position": "CF",
    "fetched": "2026-05-06"
  },
  "802415": {
    "position": "LF",
    "fetched": "2026-05-06"
  },
  "669288": {
    "position": "CF",
    "fetched": "2026-05-06"
  },
  "650490": {
    "position": "DH",
    "fetched": "2026-05-06"
  },
  "641584": {
    "position": "RF",
    "fetched": "2026-05-06"
  },
  "691406": {
    "position": "3B",
    "fetched": "2026-05-06"
  },
  "666018": {
    "position": "1B",
    "fetched": "2026-05-06"
  },
  "680700": {
    "position": "2B",
    "fetched": "2026-05-06"
  },
  "670764": {
    "position": "SS",
    "fetched": "2026-05-06"
  },
  "691718": {
    "position": "CF",
    "fetched": "2026-05-06"
  },
  "516782": {
    "position": "RF",
    "fetched": "2026-05-06"
  },
  "669087": {
    "position": "C",
    "fetched": "2026-05-06"
  },
  "624424": {
    "position": "RF",
    "fetched": "2026-05-06"
  },
  "665804": {
    "position": "C",
    "fetched": "2026-05-06"
  },
  "645302": {
    "position": "RF",
    "fetched": "2026-05-06"
  },
  "671286": {
    "position": "RF",
    "fetched": "2026-05-06"
  },
  "642215": {
    "position": "3B",
    "fetched": "2026-05-06"
  },
  "678218": {
    "position": "C",
    "fetched": "2026-05-06"
  },
  "666211": {
    "position": "CF",
    "fetched": "2026-05-06"
  },
  "676356": {
    "position": "RF",
    "fetched": "2026-05-06"
  },
  "668723": {
    "position": "RF",
    "fetched": "2026-05-06"
  },
  "676439": {
    "position": "C",
    "fetched": "2026-05-06"
  },
  "666185": {
    "position": "LF",
    "fetched": "2026-05-06"
  },
  "687221": {
    "position": "C",
    "fetched": "2026-05-06"
  },
  "669208": {
    "position": "DH",
    "fetched": "2026-05-06"
  },
  "687263": {
    "position": "SS",
    "fetched": "2026-05-06"
  },
  "624585": {
    "position": "DH",
    "fetched": "2026-05-06"
  },
  "672724": {
    "position": "3B",
    "fetched": "2026-05-06"
  },
  "694384": {
    "position": "1B",
    "fetched": "2026-05-06"
  },
  "518595": {
    "position": "C",
    "fetched": "2026-05-06"
  },
  "666176": {
    "position": "RF",
    "fetched": "2026-05-06"
  },
  "545361": {
    "position": "CF",
    "fetched": "2026-05-06"
  },
  "669326": {
    "position": "LF",
    "fetched": "2026-05-06"
  },
  "666971": {
    "position": "LF",
    "fetched": "2026-05-06"
  },
  "686452": {
    "position": "C",
    "fetched": "2026-05-06"
  },
  "687093": {
    "position": "2B",
    "fetched": "2026-05-06"
  },
  "671277": {
    "position": "1B",
    "fetched": "2026-05-06"
  },
  "695578": {
    "position": "RF",
    "fetched": "2026-05-06"
  },
  "691781": {
    "position": "3B",
    "fetched": "2026-05-06"
  },
  "682928": {
    "position": "SS",
    "fetched": "2026-05-06"
  },
  "696285": {
    "position": "CF",
    "fetched": "2026-05-06"
  },
  "683083": {
    "position": "2B",
    "fetched": "2026-05-06"
  },
  "695734": {
    "position": "LF",
    "fetched": "2026-05-06"
  },
  "663624": {
    "position": "1B",
    "fetched": "2026-05-06"
  },
  "678554": {
    "position": "1B",
    "fetched": "2026-05-06"
  },
  "686894": {
    "position": "RF",
    "fetched": "2026-05-06"
  },
  "642851": {
    "position": "C",
    "fetched": "2026-05-06"
  },
  "677588": {
    "position": "DH",
    "fetched": "2026-05-06"
  },
  "672016": {
    "position": "CF",
    "fetched": "2026-05-06"
  },
  "643446": {
    "position": "2B",
    "fetched": "2026-05-06"
  },
  "687231": {
    "position": "3B",
    "fetched": "2026-05-06"
  },
  "805779": {
    "position": "SS",
    "fetched": "2026-05-06"
  },
  "691016": {
    "position": "LF",
    "fetched": "2026-05-06"
  },
  "671732": {
    "position": "RF",
    "fetched": "2026-05-06"
  },
  "678391": {
    "position": "3B",
    "fetched": "2026-05-06"
  },
  "691777": {
    "position": "3B",
    "fetched": "2026-05-06"
  },
  "688363": {
    "position": "3B",
    "fetched": "2026-05-06"
  },
  "682663": {
    "position": "C",
    "fetched": "2026-05-06"
  },
  "805300": {
    "position": "CF",
    "fetched": "2026-05-06"
  },
  "672640": {
    "position": "SS",
    "fetched": "2026-05-06"
  },
  "683357": {
    "position": "RF",
    "fetched": "2026-05-06"
  },
  "681715": {
    "position": "LF",
    "fetched": "2026-05-06"
  },
  "665052": {
    "position": "LF",
    "fetched": "2026-05-06"
  },
  "669364": {
    "position": "2B",
    "fetched": "2026-05-06"
  },
  "666126": {
    "position": "RF",
    "fetched": "2026-05-06"
  },
  "669127": {
    "position": "C",
    "fetched": "2026-05-06"
  },
  "701762": {
    "position": "1B",
    "fetched": "2026-05-06"
  },
  "689414": {
    "position": "C",
    "fetched": "2026-05-06"
  },
  "683734": {
    "position": "1B",
    "fetched": "2026-05-06"
  },
  "681393": {
    "position": "1B",
    "fetched": "2026-05-06"
  },
  "660688": {
    "position": "C",
    "fetched": "2026-05-06"
  },
  "691594": {
    "position": "3B",
    "fetched": "2026-05-06"
  },
  "624428": {
    "position": "2B",
    "fetched": "2026-05-06"
  },
  "680869": {
    "position": "CF",
    "fetched": "2026-05-06"
  },
  "691620": {
    "position": "C",
    "fetched": "2026-05-06"
  },
  "666139": {
    "position": "LF",
    "fetched": "2026-05-06"
  },
  "665861": {
    "position": "C",
    "fetched": "2026-05-06"
  },
  "660162": {
    "position": "3B",
    "fetched": "2026-05-06"
  },
  "605244": {
    "position": "C",
    "fetched": "2026-05-06"
  },
  "677870": {
    "position": "2B",
    "fetched": "2026-05-06"
  },
  "628451": {
    "position": "2B",
    "fetched": "2026-05-06"
  },
  "596103": {
    "position": "RF",
    "fetched": "2026-05-06"
  },
  "665953": {
    "position": "1B",
    "fetched": "2026-05-06"
  },
  "691783": {
    "position": "LF",
    "fetched": "2026-05-06"
  },
  "467793": {
    "position": "1B",
    "fetched": "2026-05-06"
  },
  "672515": {
    "position": "C",
    "fetched": "2026-05-06"
  },
  "677956": {
    "position": "RF",
    "fetched": "2026-05-06"
  },
  "668709": {
    "position": "LF",
    "fetched": "2026-05-06"
  },
  "691277": {
    "position": "1B",
    "fetched": "2026-05-06"
  },
  "686475": {
    "position": "2B",
    "fetched": "2026-05-06"
  },
  "686668": {
    "position": "CF",
    "fetched": "2026-05-06"
  },
  "664983": {
    "position": "LF",
    "fetched": "2026-05-06"
  },
  "681351": {
    "position": "C",
    "fetched": "2026-05-06"
  },
  "667670": {
    "position": "DH",
    "fetched": "2026-05-06"
  },
  "671289": {
    "position": "RF",
    "fetched": "2026-05-06"
  },
  "678662": {
    "position": "SS",
    "fetched": "2026-05-06"
  },
  "681198": {
    "position": "1B",
    "fetched": "2026-05-06"
  },
  "691720": {
    "position": "3B",
    "fetched": "2026-05-06"
  },
  "696100": {
    "position": "C",
    "fetched": "2026-05-06"
  },
  "687859": {
    "position": "RF",
    "fetched": "2026-05-06"
  },
  "666160": {
    "position": "LF",
    "fetched": "2026-05-06"
  },
  "666397": {
    "position": "2B",
    "fetched": "2026-05-06"
  },
  "650489": {
    "position": "2B",
    "fetched": "2026-05-06"
  },
  "687597": {
    "position": "LF",
    "fetched": "2026-05-06"
  },
  "600869": {
    "position": "1B",
    "fetched": "2026-05-06"
  },
  "664954": {
    "position": "C",
    "fetched": "2026-05-06"
  },
  "687515": {
    "position": "RF",
    "fetched": "2026-05-06"
  },
  "656716": {
    "position": "2B",
    "fetched": "2026-05-06"
  },
  "672356": {
    "position": "SS",
    "fetched": "2026-05-06"
  },
  "664731": {
    "position": "C",
    "fetched": "2026-05-06"
  },
  "691011": {
    "position": "C",
    "fetched": "2026-05-06"
  },
  "678009": {
    "position": "CF",
    "fetched": "2026-05-06"
  },
  "502054": {
    "position": "LF",
    "fetched": "2026-05-06"
  },
  "700246": {
    "position": "SS",
    "fetched": "2026-05-06"
  },
  "665742": {
    "position": "DH",
    "fetched": "2026-05-06"
  },
  "669004": {
    "position": "LF",
    "fetched": "2026-05-06"
  },
  "669699": {
    "position": "3B",
    "fetched": "2026-05-06"
  },
  "683953": {
    "position": "2B",
    "fetched": "2026-05-06"
  },
  "695257": {
    "position": "RF",
    "fetched": "2026-05-06"
  },
  "607208": {
    "position": "SS",
    "fetched": "2026-05-06"
  },
  "656582": {
    "position": "RF",
    "fetched": "2026-05-06"
  },
  "547180": {
    "position": "1B",
    "fetched": "2026-05-06"
  },
  "656941": {
    "position": "DH",
    "fetched": "2026-05-06"
  },
  "808975": {
    "position": "SS",
    "fetched": "2026-05-06"
  },
  "664761": {
    "position": "3B",
    "fetched": "2026-05-06"
  },
  "805249": {
    "position": "LF",
    "fetched": "2026-05-06"
  },
  "666969": {
    "position": "RF",
    "fetched": "2026-05-06"
  },
  "702222": {
    "position": "CF",
    "fetched": "2026-05-06"
  },
  "669016": {
    "position": "LF",
    "fetched": "2026-05-06"
  },
  "681082": {
    "position": "2B",
    "fetched": "2026-05-06"
  },
  "592663": {
    "position": "C",
    "fetched": "2026-05-06"
  },
  "691176": {
    "position": "DH",
    "fetched": "2026-05-06"
  },
  "669289": {
    "position": "2B",
    "fetched": "2026-05-06"
  },
  "669743": {
    "position": "LF",
    "fetched": "2026-05-06"
  },
  "664238": {
    "position": "1B",
    "fetched": "2026-05-06"
  },
  "624641": {
    "position": "2B",
    "fetched": "2026-05-06"
  },
  "675659": {
    "position": "LF",
    "fetched": "2026-05-06"
  },
  "690022": {
    "position": "2B",
    "fetched": "2026-05-06"
  },
  "690924": {
    "position": "DH",
    "fetched": "2026-05-06"
  },
  "665561": {
    "position": "C",
    "fetched": "2026-05-06"
  },
  "672012": {
    "position": "DH",
    "fetched": "2026-05-06"
  },
  "596117": {
    "position": "C",
    "fetched": "2026-05-06"
  },
  "694025": {
    "position": "LF",
    "fetched": "2026-05-06"
  },
  "686823": {
    "position": "LF",
    "fetched": "2026-05-06"
  },
  "687551": {
    "position": "CF",
    "fetched": "2026-05-06"
  },
  "669899": {
    "position": "1B",
    "fetched": "2026-05-06"
  },
  "656976": {
    "position": "DH",
    "fetched": "2026-05-06"
  },
  "669065": {
    "position": "LF",
    "fetched": "2026-05-06"
  },
  "670032": {
    "position": "3B",
    "fetched": "2026-05-06"
  },
  "673548": {
    "position": "RF",
    "fetched": "2026-05-06"
  },
  "666624": {
    "position": "1B",
    "fetched": "2026-05-06"
  },
  "606992": {
    "position": "C",
    "fetched": "2026-05-06"
  },
  "664068": {
    "position": "DH",
    "fetched": "2026-05-06"
  },
  "621550": {
    "position": "DH",
    "fetched": "2026-05-06"
  },
  "665923": {
    "position": "RF",
    "fetched": "2026-05-06"
  },
  "669717": {
    "position": "3B",
    "fetched": "2026-05-06"
  },
  "656180": {
    "position": null,
    "fetched": "2026-05-06"
  },
  "686611": {
    "position": null,
    "fetched": "2026-05-06"
  },
  "690987": {
    "position": null,
    "fetched": "2026-05-06"
  },
  "694673": {
    "position": null,
    "fetched": "2026-05-06"
  },
  "691002": {
    "position": null,
    "fetched": "2026-05-06"
  },
  "687605": {
    "position": null,
    "fetched": "2026-05-06"
  },
  "681047": {
    "position": null,
    "fetched": "2026-05-06"
  },
  "702358": {
    "position": null,
    "fetched": "2026-05-06"
  },
  "670097": {
    "position": "SS",
    "fetched": "2026-05-06"
  },
  "701298": {
    "position": null,
    "fetched": "2026-05-06"
  },
  "695670": {
    "position": null,
    "fetched": "2026-05-06"
  },
  "668663": {
    "position": null,
    "fetched": "2026-05-06"
  },
  "682119": {
    "position": null,
    "fetched": "2026-05-06"
  },
  "672284": {
    "position": "RF",
    "fetched": "2026-05-06"
  },
  "680474": {
    "position": "RF",
    "fetched": "2026-05-06"
  },
  "690291": {
    "position": "DH",
    "fetched": "2026-05-06"
  },
  "690984": {
    "position": "CF",
    "fetched": "2026-05-06"
  },
  "695391": {
    "position": "3B",
    "fetched": "2026-05-06"
  },
  "640902": {
    "position": "C",
    "fetched": "2026-05-06"
  },
  "640492": {
    "position": "RF",
    "fetched": "2026-05-06"
  },
  "669221": {
    "position": "C",
    "fetched": "2026-05-06"
  },
  "805904": {
    "position": "LF",
    "fetched": "2026-05-06"
  },
  "691788": {
    "position": "C",
    "fetched": "2026-05-06"
  },
  "805811": {
    "position": "DH",
    "fetched": "2026-05-06"
  },
  "683679": {
    "position": "C",
    "fetched": "2026-05-06"
  },
  "694192": {
    "position": "LF",
    "fetched": "2026-05-06"
  },
  "679822": {
    "position": null,
    "fetched": "2026-05-06"
  },
  "823550": {
    "position": "2B",
    "fetched": "2026-05-06"
  }
}